raana/__init__.py
raana/calibration.py
raana/main.py
raana/quantized_linear.py
raana/select_layers.py
raana/dp/__init__.py
raana/dp/dp.cp310-win_amd64.pyd
raana/dp/dp.cpp
raana/rabitq/__init__.py
raana/rabitq/rabitq.cp310-win_amd64.pyd
raana/rabitq/rabitq.cpp
raana/rotations/__init__.py
raana/rotations/base.py
raana/rotations/piecewise_hadamard.py
raana/task_adaptor/__init__.py
raana/task_adaptor/base.py
raana/task_adaptor/lm.py
raana/tricks/__init__.py
raana/tricks/base.py
raana/tricks/centralize.py
raana/tricks/norm_col.py
raana/tricks/norm_row.py
raana/tricks/principle.py
raana-0.1.0.dist-info/licenses/LICENSE
raana-0.1.0.dist-info/METADATA
raana-0.1.0.dist-info/WHEEL
raana-0.1.0.dist-info/top_level.txt
raana-0.1.0.dist-info/RECORD
