Metadata-Version: 2.4
Name: RaanA
Version: 0.1.0
Summary: RaanA quantization algorithm
Author-email: Yongyi Yang <yongyi@umich.edu>
License: MIT
Project-URL: Homepage, https://github.com/FFTYYY/RaanA
Project-URL: Repository, https://github.com/FFTYYY/RaanA
Classifier: Programming Language :: Python :: 3
Classifier: License :: OSI Approved :: MIT License
Classifier: Operating System :: OS Independent
Requires-Python: >=3.10
License-File: LICENSE
Requires-Dist: torch
Requires-Dist: transformers>=4.46.2
Requires-Dist: datasets>=3.1.0
Requires-Dist: tqdm>=4.67.0
Requires-Dist: scipy>=1.14.1
Requires-Dist: scikit-learn>=1.5.2
Requires-Dist: pybind11>=2.6.0
Dynamic: license-file
